[
  {
    "key": "group_erh_performance_tests",
    "title": "Performance Tests",
    "fields": [
      {
        "key": "field_61531f74886e7",
        "label": "Tested Top Speed",
        "name": "tested_top_speed",
        "aria-label": "",
        "type": "number",
        "instructions": "",
        "required": 0,
        "wrapper": {
          "width": "16",
          "class": "",
          "id": ""
        },
        "default_value": "",
        "min": "",
        "max": "",
        "placeholder": "",
        "step": "",
        "prepend": "",
        "append": "MPH"
      },
      {
        "key": "field_erh_acceleration_0_15_mph",
        "label": "Acceleration 0-15 MPH",
        "name": "acceleration_0_15_mph",
        "aria-label": "",
        "type": "number",
        "instructions": "",
        "required": 0,
        "wrapper": {
          "width": "16",
          "class": "",
          "id": ""
        },
        "default_value": "",
        "min": "",
        "max": "",
        "placeholder": "",
        "step": "",
        "prepend": "",
        "append": "secs"
      },
      {
        "key": "field_erh_acceleration_0_20_mph",
        "label": "Acceleration 0-20 MPH",
        "name": "acceleration_0_20_mph",
        "aria-label": "",
        "type": "number",
        "instructions": "",
        "required": 0,
        "wrapper": {
          "width": "16",
          "class": "",
          "id": ""
        },
        "default_value": "",
        "min": "",
        "max": "",
        "placeholder": "",
        "step": "",
        "prepend": "",
        "append": "secs"
      },
      {
        "key": "field_erh_acceleration_0_25_mph",
        "label": "Acceleration 0-25 MPH",
        "name": "acceleration_0_25_mph",
        "aria-label": "",
        "type": "number",
        "instructions": "",
        "required": 0,
        "wrapper": {
          "width": "16",
          "class": "",
          "id": ""
        },
        "default_value": "",
        "min": "",
        "max": "",
        "placeholder": "",
        "step": "",
        "prepend": "",
        "append": "secs"
      },
      {
        "key": "field_erh_acceleration_0_30_mph",
        "label": "Acceleration 0-30 MPH",
        "name": "acceleration_0_30_mph",
        "aria-label": "",
        "type": "number",
        "instructions": "",
        "required": 0,
        "wrapper": {
          "width": "16",
          "class": "",
          "id": ""
        },
        "default_value": "",
        "min": "",
        "max": "",
        "placeholder": "",
        "step": "",
        "prepend": "",
        "append": "secs"
      },
      {
        "key": "field_erh_acceleration_0_to_top",
        "label": "Acceleration 0-Top",
        "name": "acceleration_0_to_top",
        "aria-label": "",
        "type": "number",
        "instructions": "",
        "required": 0,
        "wrapper": {
          "width": "16",
          "class": "",
          "id": ""
        },
        "default_value": "",
        "min": "",
        "max": "",
        "placeholder": "",
        "step": "",
        "prepend": "",
        "append": "secs"
      },
      {
        "key": "field_639215a043dfd",
        "label": "Fastest 0-15 MPH",
        "name": "fastest_0_15",
        "aria-label": "",
        "type": "number",
        "instructions": "",
        "required": 0,
        "wrapper": {
          "width": "16",
          "class": "",
          "id": ""
        },
        "default_value": "",
        "min": "",
        "max": "",
        "placeholder": "",
        "step": "",
        "prepend": "",
        "append": "secs"
      },
      {
        "key": "field_639215b443dfe",
        "label": "Fastest 0-20 MPH",
        "name": "fastest_0_20",
        "aria-label": "",
        "type": "number",
        "instructions": "",
        "required": 0,
        "wrapper": {
          "width": "16",
          "class": "",
          "id": ""
        },
        "default_value": "",
        "min": "",
        "max": "",
        "placeholder": "",
        "step": "",
        "prepend": "",
        "append": "secs"
      },
      {
        "key": "field_639215ba43dff",
        "label": "Fastest 0-25 MPH",
        "name": "fastest_0_25",
        "aria-label": "",
        "type": "number",
        "instructions": "",
        "required": 0,
        "wrapper": {
          "width": "16",
          "class": "",
          "id": ""
        },
        "default_value": "",
        "min": "",
        "max": "",
        "placeholder": "",
        "step": "",
        "prepend": "",
        "append": "secs"
      },
      {
        "key": "field_639215c343e00",
        "label": "Fastest 0-30 MPH",
        "name": "fastest_0_30",
        "aria-label": "",
        "type": "number",
        "instructions": "",
        "required": 0,
        "wrapper": {
          "width": "16",
          "class": "",
          "id": ""
        },
        "default_value": "",
        "min": "",
        "max": "",
        "placeholder": "",
        "step": "",
        "prepend": "",
        "append": "secs"
      },
      {
        "key": "field_639215c943e01",
        "label": "Fastest 0 to Top Speed",
        "name": "fastest_0_top",
        "aria-label": "",
        "type": "number",
        "instructions": "",
        "required": 0,
        "wrapper": {
          "width": "16",
          "class": "",
          "id": ""
        },
        "default_value": "",
        "min": "",
        "max": "",
        "placeholder": "",
        "step": "",
        "prepend": "",
        "append": "secs"
      },
      {
        "key": "field_61531f8e886e8",
        "label": "Tested Range (Speed Priority)",
        "name": "tested_range_fast",
        "aria-label": "",
        "type": "number",
        "instructions": "",
        "required": 0,
        "wrapper": {
          "width": "16",
          "class": "",
          "id": ""
        },
        "default_value": "",
        "placeholder": "",
        "prepend": "",
        "append": "miles",
        "min": "",
        "max": "",
        "step": ""
      },
      {
        "key": "field_61531fb1886e9",
        "label": "Tested Range (Regular)",
        "name": "tested_range_regular",
        "aria-label": "",
        "type": "number",
        "instructions": "",
        "required": 0,
        "wrapper": {
          "width": "16",
          "class": "",
          "id": ""
        },
        "default_value": "",
        "placeholder": "",
        "prepend": "",
        "append": "miles",
        "min": "",
        "max": "",
        "step": ""
      },
      {
        "key": "field_61531fb9886ea",
        "label": "Tested Range (Range Priority)",
        "name": "tested_range_slow",
        "aria-label": "",
        "type": "number",
        "instructions": "",
        "required": 0,
        "wrapper": {
          "width": "16",
          "class": "",
          "id": ""
        },
        "default_value": "",
        "placeholder": "",
        "prepend": "",
        "append": "miles",
        "min": "",
        "max": "",
        "step": ""
      },
      {
        "key": "field_615320ce2b6c2",
        "label": "Tested Range Avg. Speed (Speed Priority)",
        "name": "tested_range_avg_speed_fast",
        "aria-label": "",
        "type": "number",
        "instructions": "",
        "required": 0,
        "wrapper": {
          "width": "16",
          "class": "",
          "id": ""
        },
        "default_value": "",
        "placeholder": "",
        "prepend": "",
        "append": "MPH",
        "min": "",
        "max": "",
        "step": ""
      },
      {
        "key": "field_615320e82b6c3",
        "label": "Tested Range Avg. Speed (Regular)",
        "name": "tested_range_avg_speed_regular",
        "aria-label": "",
        "type": "number",
        "instructions": "",
        "required": 0,
        "wrapper": {
          "width": "16",
          "class": "",
          "id": ""
        },
        "default_value": "",
        "placeholder": "",
        "prepend": "",
        "append": "MPH",
        "min": "",
        "max": "",
        "step": ""
      },
      {
        "key": "field_615320f72b6c4",
        "label": "Tested Range Avg. Speed (Range Priority)",
        "name": "tested_range_avg_speed_slow",
        "aria-label": "",
        "type": "number",
        "instructions": "",
        "required": 0,
        "wrapper": {
          "width": "16",
          "class": "",
          "id": ""
        },
        "default_value": "",
        "placeholder": "",
        "prepend": "",
        "append": "MPH",
        "min": "",
        "max": "",
        "step": ""
      },
      {
        "key": "field_61a4a99b40e64",
        "label": "Brake distance",
        "name": "brake_distance",
        "aria-label": "",
        "type": "number",
        "instructions": "",
        "required": 0,
        "wrapper": {
          "width": "16",
          "class": "",
          "id": ""
        },
        "default_value": "",
        "min": "",
        "max": "",
        "placeholder": "",
        "step": "",
        "prepend": "",
        "append": "ft"
      },
      {
        "key": "field_647f4ec2653f9",
        "label": "Hill Climbing",
        "name": "hill_climbing",
        "aria-label": "",
        "type": "number",
        "instructions": "",
        "required": 0,
        "wrapper": {
          "width": "16",
          "class": "",
          "id": ""
        },
        "default_value": "",
        "min": "",
        "max": "",
        "placeholder": "",
        "step": "",
        "prepend": "",
        "append": "seconds"
      },
      {
        "key": "field_61532c139ce55",
        "label": "Manufacturer Top Speed",
        "name": "manufacturer_top_speed",
        "aria-label": "",
        "type": "number",
        "instructions": "",
        "required": 0,
        "wrapper": {
          "width": "16",
          "class": "",
          "id": ""
        },
        "default_value": "",
        "placeholder": "",
        "prepend": "",
        "append": "MPH",
        "min": "",
        "max": "",
        "step": ""
      },
      {
        "key": "field_61532c219ce56",
        "label": "Manufacturer Range",
        "name": "manufacturer_range",
        "aria-label": "",
        "type": "number",
        "instructions": "",
        "required": 0,
        "wrapper": {
          "width": "16",
          "class": "",
          "id": ""
        },
        "default_value": "",
        "placeholder": "",
        "prepend": "",
        "append": "miles",
        "min": "",
        "max": "",
        "step": ""
      },
      {
        "key": "field_652c026c68432",
        "label": "Max incline",
        "name": "max_incline",
        "aria-label": "",
        "type": "number",
        "instructions": "",
        "required": 0,
        "wrapper": {
          "width": "16",
          "class": "",
          "id": ""
        },
        "default_value": "",
        "min": "",
        "max": "",
        "placeholder": "",
        "step": "",
        "prepend": "",
        "append": "degrees"
      },
      {
        "key": "field_652c028768433",
        "label": "Ideal incline",
        "name": "ideal_incline",
        "aria-label": "",
        "type": "number",
        "instructions": "",
        "required": 0,
        "wrapper": {
          "width": "16",
          "class": "",
          "id": ""
        },
        "default_value": "",
        "min": "",
        "max": "",
        "placeholder": "",
        "step": "",
        "prepend": "",
        "append": "degrees"
      }
    ],
    "location": [
      [
        {
          "param": "post_type",
          "operator": "==",
          "value": "products"
        }
      ]
    ],
    "menu_order": 1,
    "position": "normal",
    "style": "default",
    "label_placement": "top",
    "instruction_placement": "label",
    "hide_on_screen": "",
    "active": true,
    "show_in_rest": true
  }
]